jomllib/__init__.py
jomllib/_parser.py
jomllib/_re.py
jomllib/_types.py
jomllib-1.0.0.dist-info/METADATA
jomllib-1.0.0.dist-info/WHEEL
jomllib-1.0.0.dist-info/licenses/LICENSE.md
jomllib-1.0.0.dist-info/RECORD
